pulumi_scm/__init__.py
pulumi_scm/_inputs.py
pulumi_scm/_utilities.py
pulumi_scm/address.py
pulumi_scm/address_group.py
pulumi_scm/aggregate_ethernet_interface.py
pulumi_scm/anti_spyware_profile.py
pulumi_scm/anti_spyware_signature.py
pulumi_scm/app_override_rule.py
pulumi_scm/application.py
pulumi_scm/application_filter.py
pulumi_scm/application_group.py
pulumi_scm/authentication_profile.py
pulumi_scm/authentication_rule.py
pulumi_scm/authentication_sequence.py
pulumi_scm/bgp_address_family_profile.py
pulumi_scm/bgp_auth_profile.py
pulumi_scm/bgp_filtering_profile.py
pulumi_scm/bgp_redistribution_profile.py
pulumi_scm/bgp_route_map.py
pulumi_scm/bgp_route_map_redistribution.py
pulumi_scm/certificate_profile.py
pulumi_scm/decryption_exclusion.py
pulumi_scm/decryption_profile.py
pulumi_scm/decryption_rule.py
pulumi_scm/dhcp_interface.py
pulumi_scm/dns_proxy.py
pulumi_scm/dns_security_profile.py
pulumi_scm/dos_protection_profile.py
pulumi_scm/dos_protection_rule.py
pulumi_scm/dynamic_user_group.py
pulumi_scm/ethernet_interface.py
pulumi_scm/external_dynamic_list.py
pulumi_scm/file_blocking_profile.py
pulumi_scm/folder.py
pulumi_scm/get_address.py
pulumi_scm/get_address_group.py
pulumi_scm/get_address_group_list.py
pulumi_scm/get_address_list.py
pulumi_scm/get_aggregate_ethernet_interface.py
pulumi_scm/get_aggregate_ethernet_interface_list.py
pulumi_scm/get_anti_spyware_profile.py
pulumi_scm/get_anti_spyware_profile_list.py
pulumi_scm/get_anti_spyware_signature.py
pulumi_scm/get_anti_spyware_signature_list.py
pulumi_scm/get_app_override_rule.py
pulumi_scm/get_app_override_rule_list.py
pulumi_scm/get_application.py
pulumi_scm/get_application_filter.py
pulumi_scm/get_application_filter_list.py
pulumi_scm/get_application_group.py
pulumi_scm/get_application_group_list.py
pulumi_scm/get_application_list.py
pulumi_scm/get_authentication_profile.py
pulumi_scm/get_authentication_profile_list.py
pulumi_scm/get_authentication_rule.py
pulumi_scm/get_authentication_rule_list.py
pulumi_scm-1.0.0.dist-info/METADATA
pulumi_scm-1.0.0.dist-info/WHEEL
pulumi_scm-1.0.0.dist-info/top_level.txt
pulumi_scm-1.0.0.dist-info/RECORD
